langextract_deepseek/__init__.py
langextract_deepseek/provider.py
langextract_deepseek-0.1.0.dist-info/METADATA
langextract_deepseek-0.1.0.dist-info/WHEEL
langextract_deepseek-0.1.0.dist-info/entry_points.txt
langextract_deepseek-0.1.0.dist-info/top_level.txt
langextract_deepseek-0.1.0.dist-info/RECORD
