Metadata-Version: 2.4
Name: langextract-deepseek
Version: 0.1.0
Summary: DeepSeek provider plugin for LangExtract
Author-email: Your Name <your@email.com>
Requires-Dist: langextract>=1.0.0
Requires-Dist: requests
